trytond/modules/translation_override_de/__init__.py
trytond/modules/translation_override_de/tryton.cfg
trytond/modules/translation_override_de/tests/__init__.py
trytond/modules/translation_override_de/tests/test_translation_override_de.py
m9s_translation_override_de-6.0.0.dist-info/LICENSE
m9s_translation_override_de-6.0.0.dist-info/METADATA
m9s_translation_override_de-6.0.0.dist-info/WHEEL
m9s_translation_override_de-6.0.0.dist-info/entry_points.txt
m9s_translation_override_de-6.0.0.dist-info/top_level.txt
m9s_translation_override_de-6.0.0.dist-info/RECORD
